thingsmatrix/__init__.py
thingsmatrix/apis.py
thingsmatrix/gredients.py
thingsmatrix/main.py
thingsmatrix/objects.py
thingsmatrix-0.7.0.dist-info/entry_points.txt
thingsmatrix-0.7.0.dist-info/WHEEL
thingsmatrix-0.7.0.dist-info/METADATA
thingsmatrix-0.7.0.dist-info/RECORD
