Metadata-Version: 2.1
Name: thingsmatrix
Version: 0.7.0
Summary: 
Author: yooooyo
Author-email: loipswqe@gmail.com
Requires-Python: >=3.9,<4.0
Classifier: Programming Language :: Python :: 3
Classifier: Programming Language :: Python :: 3.10
Classifier: Programming Language :: Python :: 3.9
Requires-Dist: python-dateutil (>=2.8.2,<3.0.0)
Requires-Dist: requests (>=2.27.1,<3.0.0)
Requires-Dist: rich (>=12.0.1,<13.0.0)
Requires-Dist: typer (>=0.4.0,<0.5.0)
